deal_distiller/__init__.py
deal_distiller/main.py
deal_distiller/prompts.py
deal_distiller-2025.12.21080604.dist-info/METADATA
deal_distiller-2025.12.21080604.dist-info/WHEEL
deal_distiller-2025.12.21080604.dist-info/top_level.txt
deal_distiller-2025.12.21080604.dist-info/RECORD
