Metadata-Version: 2.4
Name: deal-distiller
Version: 2025.12.21080604
Summary: This package aims to distill complex business and technology news into easily digestible summaries, focusing on the core implications and potential impact of mergers and acquisitions. It tackles the p
Author-email: deal-distiller <hi@eugene.plus>
License: MIT
Project-URL: Homepage, https://github.com/chigwell/deal-distiller
Requires-Python: >=3.9
Requires-Dist: langchain-llm7>=0.0.0
Requires-Dist: llmatch-messages>=0.0.0
Requires-Dist: langchain-core>=0.3.0
